{
    "Version": "2012-10-17",
    "Statement": [
      {
        "Effect": "Allow",
        "Action": [
          "api:CreateInternetService",
          "api:CreateKeypair",
          "api:CreateLoadBalancer",
          "api:CreateLoadBalancerTags",
          "api:CreateNatService",
          "api:CreateNet",
          "api:CreateNetAccessPoint",
          "api:CreateNetPeering",
          "api:CreatePublicIp",
          "api:CreateRoute",
          "api:CreateRouteTable",
          "api:CreateSecurityGroup",
          "api:CreateSecurityGroupRule",
          "api:CreateSubnet",
          "api:CreateTags",
          "api:CreateVms",
          "api:DeleteNetAccessPoint",
          "api:DeleteNetPeering",
          "api:DeleteInternetService",
          "api:DeleteKeypair",
          "api:DeleteLoadBalancer",
          "api:DeleteLoadBalancerTags",
          "api:DeleteNatService",
          "api:DeleteNet",
          "api:DeletePublicIp",
          "api:DeleteRoute",
          "api:DeleteRouteTable",
          "api:DeleteSecurityGroup",
          "api:DeleteSecurityGroupRule",
          "api:DeleteSubnet",
          "api:DeleteTags",
          "api:DeleteVms",
          "api:DeleteVolume",
          "api:GetApi",
          "api:AcceptNetPeering",
          "api:LinkInternetService",
          "api:LinkLoadBalancerBackendMachines",
          "api:LinkRouteTable",
          "api:ReadNetAccessPoints",
          "api:ReadNetPeerings",
          "api:ReadImages",
          "api:ReadInternetServices",
          "api:ReadKeypairs",
          "api:ReadLoadBalancerTags",
          "api:ReadLoadBalancers",
          "api:ReadNatServices",
          "api:ReadNets",
          "api:ReadPublicIps",
          "api:ReadRouteTables",
          "api:ReadSecurityGroups",
          "api:ReadSubnets",
          "api:ReadTags",
          "api:ReadVms",
          "api:ReadVolumes",
          "api:UnlinkInternetService",
          "api:UnlinkLoadBalancerBackendMachines",
          "api:UnlinkRouteTable",
          "api:",
          "api:UpdateLoadBalancer"
        ],
        "Resource": "*"
      }
    ]
  }
